chart_vendor/__init__.py
chart_vendor/cli.py
chart_vendor/models.py
chart_vendor/parsers.py
chart_vendor-0.2.0.dist-info/AUTHORS
chart_vendor-0.2.0.dist-info/METADATA
chart_vendor-0.2.0.dist-info/WHEEL
chart_vendor-0.2.0.dist-info/entry_points.txt
chart_vendor-0.2.0.dist-info/pbr.json
chart_vendor-0.2.0.dist-info/top_level.txt
chart_vendor-0.2.0.dist-info/RECORD
